MANIFEST.in
setup.py
bas7ion.egg-info/PKG-INFO
bas7ion.egg-info/SOURCES.txt
bas7ion.egg-info/dependency_links.txt
bas7ion.egg-info/requires.txt
bas7ion.egg-info/top_level.txt
bastion/__init__.py
bastion/component.py
bastion/driver.py
bastion/provider_types.py
bastion/authentication/__init__.py
bastion/authentication/base.py
bastion/authentication/vault.py
bastion/compute/__init__.py
bastion/compute/aws.py
bastion/compute/azure.py
bastion/compute/base.py
bastion/compute/common/__init__.py
bastion/compute/common/image.py
bastion/compute/common/size.py
bastion/compute/vm/__init__.py
bastion/compute/vm/aws.py
bastion/compute/vm/azure.py
bastion/compute/vm/base.py
bastion/libcloudbastion/__init__.py
bastion/libcloudbastion/azure_arm.py
bastion/libcloudbastion/driver.py
bastion/libcloudbastion/driver_dns.py
bastion/libcloudbastion/ec2.py
bastion/libcloudbastion/route53.py
bastion/networking/__init__.py
bastion/networking/aws.py
bastion/networking/azure.py
bastion/networking/base.py
bastion/networking/gateway/__init__.py
bastion/networking/gateway/aws.py
bastion/networking/gateway/base.py
bastion/networking/network/__init__.py
bastion/networking/network/aws.py
bastion/networking/network/azure.py
bastion/networking/network/base.py
bastion/networking/network_interface/__init__.py
bastion/networking/network_interface/aws.py
bastion/networking/network_interface/azure.py
bastion/networking/network_interface/base.py
bastion/networking/private_dns/__init__.py
bastion/networking/private_dns/aws.py
bastion/networking/private_dns/azure.py
bastion/networking/private_dns/base.py
bastion/networking/route_table/__init__.py
bastion/networking/route_table/aws.py
bastion/networking/route_table/azure.py
bastion/networking/route_table/base.py
bastion/networking/security_group/__init__.py
bastion/networking/security_group/aws.py
bastion/networking/security_group/azure.py
bastion/networking/security_group/base.py
bastion/networking/subnet/__init__.py
bastion/networking/subnet/aws.py
bastion/networking/subnet/azure.py
bastion/networking/subnet/base.py
bastion/playbooks/bertvv-bind.yml
bastion/playbooks/ipsec-restart.yml
